tiklocal/__init__.py
tiklocal/app.py
tiklocal/config.py
tiklocal/dedupe.py
tiklocal/paths.py
tiklocal/run.py
tiklocal/services/__init__.py
tiklocal/services/metadata.py
tiklocal/services/thumbnail.py
tiklocal/static/feather.min.js
tiklocal/static/hammer.min.js
tiklocal/static/input.css
tiklocal/static/output.css
tiklocal/templates/base.html
tiklocal/templates/browse.html
tiklocal/templates/delete_confirm.html
tiklocal/templates/detail.html
tiklocal/templates/favorite.html
tiklocal/templates/gallery.html
tiklocal/templates/image_detail.html
tiklocal/templates/index.html
tiklocal/templates/settings.html
tiklocal/templates/tiktok.html
tiklocal/thumbs.py
tiklocal-0.8.1.dist-info/METADATA
tiklocal-0.8.1.dist-info/WHEEL
tiklocal-0.8.1.dist-info/entry_points.txt
tiklocal-0.8.1.dist-info/licenses/LICENSE
tiklocal-0.8.1.dist-info/RECORD
