Metadata-Version: 2.4
Name: TikLocal
Version: 0.8.1
Summary: A local media server that combines the features of TikTok and Pinterest
License: MIT
License-File: LICENSE
Keywords: tiklocal,tiktok,douyin,jellyfin,vlc
Author: ChanMo
Author-email: chan.mo@outlook.com
Requires-Python: >=3.10,<4.0
Classifier: License :: OSI Approved :: MIT License
Classifier: Programming Language :: Python :: 3
Classifier: Programming Language :: Python :: 3.10
Classifier: Programming Language :: Python :: 3.11
Classifier: Programming Language :: Python :: 3.12
Classifier: Programming Language :: Python :: 3.13
Classifier: Programming Language :: Python :: 3.14
Requires-Dist: flask (>=3.1.0,<4.0.0)
Requires-Dist: pyyaml (>=6.0,<7.0)
Requires-Dist: requests (>=2.32.0,<3.0.0)
Requires-Dist: waitress (>=3.0.2,<4.0.0)
Project-URL: Homepage, https://github.com/ChanMo/TikLocal
Project-URL: Repository, https://github.com/ChanMo/TikLocal
